LICENSE
README.md
setup.cfg
setup.py
ml_pckg/__init__.py
ml_pckg/classifiers.py
ml_pckg/data_processing.py
ml_pckg/linear_algebra.py
ml_pckg/metrics.py
ml_pckg/regressors.py
ml_pckg.egg-info/PKG-INFO
ml_pckg.egg-info/SOURCES.txt
ml_pckg.egg-info/dependency_links.txt
ml_pckg.egg-info/requires.txt
ml_pckg.egg-info/top_level.txt